Workbook

Sheet Menu
B2: ORGANIZADOR DE IMPOSTO DE RENDA
B4: ="Contribuinte: "&'Dados Pessoais'!B6&" | Ano-calendário: "&'Dados Pessoais'!B9 -> Contribuinte: Maria da Silva (exemplo) | Ano-calendário: 2026
B6: NAVEGAÇÃO
B7: =HYPERLINK("#'Resumo'!A1","📊 Resumo da declaração") -> 📊 Resumo da declaração | C7: Totais calculados automaticamente
B8: =HYPERLINK("#'Dados Pessoais'!A1","👤 Dados pessoais e dependentes") -> 👤 Dados pessoais e dependentes | C8: Cadastro do contribuinte
B9: =HYPERLINK("#'Rendimentos'!A1","💰 Rendimentos") -> 💰 Rendimentos | C9: Salários, aluguéis, isentos e retenções
B10: =HYPERLINK("#'Despesas'!A1","🧾 Despesas dedutíveis") -> 🧾 Despesas dedutíveis | C10: Saúde, educação, previdência
B11: =HYPERLINK("#'Bens e Direitos'!A1","🏠 Bens e direitos") -> 🏠 Bens e direitos | C11: Imóveis, veículos, contas, investimentos
B12: =HYPERLINK("#'Dívidas'!A1","💳 Dívidas e ônus") -> 💳 Dívidas e ônus | C12: Financiamentos e empréstimos
B13: =HYPERLINK("#'Checklist'!A1","✅ Checklist de documentos") -> ✅ Checklist de documentos | C13: Acompanhe o que já foi reunido
B15: LINKS RÁPIDOS
B16: =HYPERLINK("https://www.gov.br/receitafederal/pt-br/assuntos/meu-imposto-de-renda","🌐 Receita Federal (IRPF)") -> 🌐 Receita Federal (IRPF)
B17: =HYPERLINK("https://cav.receita.fazenda.gov.br/","🔐 Portal e-CAC") -> 🔐 Portal e-CAC
B18: =HYPERLINK("https://www.gov.br/","🏛 Portal gov.br") -> 🏛 Portal gov.br
B20: COMO USAR
B21: • Células amarelas com texto azul = você preenche.
B22: • Células cinza = fórmulas automáticas (não edite).
B23: • Linha 6 de cada aba é um EXEMPLO: substitua ou apague.
B24: • Menus suspensos e validações evitam erros de digitação.
B25: • Confira os parâmetros (limites) na aba Resumo antes de declarar.
B27: Ferramenta de organização pessoal — não substitui orientação contábil nem o programa oficial da Receita Federal.

Sheet Resumo
A1: =HYPERLINK("#'Menu'!A1","⬅ Voltar ao Menu") -> ⬅ Voltar ao Menu
A2: Resumo da declaração
A3: Tudo aqui é calculado automaticamente a partir das outras abas — não digite nada.
A5: Identificação
A6: Contribuinte | B6: ='Dados Pessoais'!B6 -> Maria da Silva (exemplo)
A7: Ano-calendário | B7: ='Dados Pessoais'!B9 -> 2026
A8: Nº de dependentes | B8: ='Dados Pessoais'!B30 -> 1
A10: Parâmetros (confirme os valores oficiais do ano)
A11: Limite anual de dedução com educação (por pessoa) | B11: 3561.5 | C11: Valor de referência — confirme na Receita Federal
A12: Dedução anual por dependente | B12: 2275.08 | C12: Valor de referência — confirme na Receita Federal
A14: Rendimentos
A15: Tributável (salário, aluguel, autônomo) | B15: =SUMIF(Rendimentos!$D$6:$D$205,"Tributável (salário, aluguel, autônomo)",Rendimentos!$E$6:$E$205) -> 4500
A16: Isento e não tributável | B16: =SUMIF(Rendimentos!$D$6:$D$205,"Isento e não tributável",Rendimentos!$E$6:$E$205) -> 0
A17: Tributação exclusiva/definitiva | B17: =SUMIF(Rendimentos!$D$6:$D$205,"Tributação exclusiva/definitiva",Rendimentos!$E$6:$E$205) -> 0
A18: Outros | B18: =SUMIF(Rendimentos!$D$6:$D$205,"Outros",Rendimentos!$E$6:$E$205) -> 0
A19: Total de rendimentos | B19: =SUM(B15:B18) -> 4500
A20: Imposto retido na fonte | B20: =SUM(Rendimentos!F6:F205) -> 320.5
A22: Despesas dedutíveis
A23: Saúde | B23: =SUMIF(Despesas!$B$6:$B$205,"Saúde",Despesas!$E$6:$E$205) -> 350
A24: Educação | B24: =SUMIF(Despesas!$B$6:$B$205,"Educação",Despesas!$E$6:$E$205) -> 0
A25: Previdência (PGBL) | B25: =SUMIF(Despesas!$B$6:$B$205,"Previdência (PGBL)",Despesas!$E$6:$E$205) -> 0
A26: Pensão alimentícia | B26: =SUMIF(Despesas!$B$6:$B$205,"Pensão alimentícia",Despesas!$E$6:$E$205) -> 0
A27: Doação | B27: =SUMIF(Despesas!$B$6:$B$205,"Doação",Despesas!$E$6:$E$205) -> 0
A28: Outras | B28: =SUMIF(Despesas!$B$6:$B$205,"Outras",Despesas!$E$6:$E$205) -> 0
A29: Total lançado | B29: =SUM(B23:B28) -> 350
A30: Educação dedutível (aplicando o limite) | B30: =MIN(B24,B11*(1+B8)) -> 0 | C30: Limite × (titular + dependentes)
A31: Despesas sem comprovante | B31: =COUNTIF(Despesas!F6:F205,"Não") -> 0 | C31: Regularize antes de declarar
A33: Patrimônio
A34: Bens e direitos — ano anterior | B34: =SUM('Bens e Direitos'!D6:D205) -> 45000
A35: Bens e direitos — ano-calendário | B35: =SUM('Bens e Direitos'!E6:E205) -> 42000
A36: Variação patrimonial dos bens | B36: =B35-B34 -> -3000
A37: Dívidas — ano-calendário | B37: =SUM(Dívidas!E6:E205) -> 15000
A38: Patrimônio líquido | B38: =B35-B37 -> 27000
A40: Documentos
A41: Checklist concluído | B41: =Checklist!B19 -> 0

Sheet Dados Pessoais
A1: =HYPERLINK("#'Menu'!A1","⬅ Voltar ao Menu") -> ⬅ Voltar ao Menu
A2: Dados Pessoais
A3: Preencha as células amarelas (texto azul).
A5: Campo | B5: Informação
A6: Nome completo | B6: Maria da Silva (exemplo)
A7: CPF (somente números) | B7: 12345678901
A8: Data de nascimento | B8: 33013
A9: Ano-calendário (ano dos rendimentos) | B9: 2026
A10: E-mail | B10: maria@email.com
A11: Telefone | B11: (41) 99999-9999
A12: Estado civil | B12: Solteiro(a)
A13: UF | B13: PR
A14: Banco p/ restituição (opcional) | B14: Banco / Agência / Conta
A17: Dependentes
A18: Nome | B18: CPF (somente números) | C18: Parentesco | D18: Data de nascimento
A19: João da Silva (exemplo) | B19: 98765432100 | C19: Filho(a) | D19: 42073
A30: Nº de dependentes | B30: =COUNTA(A19:A28) -> 1

Sheet Rendimentos
A1: =HYPERLINK("#'Menu'!A1","⬅ Voltar ao Menu") -> ⬅ Voltar ao Menu
A2: Rendimentos
A3: Informe de rendimentos: um lançamento por linha. A linha 6 é um exemplo — substitua ou apague.
A5: Data | B5: Fonte pagadora | C5: CPF/CNPJ da fonte | D5: Tipo de rendimento | E5: Valor bruto (R$) | F5: IR retido na fonte (R$) | G5: Observação
A6: 46053 | B6: Empresa Exemplo Ltda | C6: 12345678000199 | D6: Tributável (salário, aluguel, autônomo) | E6: 4500 | F6: 320.5 | G6: Exemplo

Sheet Despesas
A1: =HYPERLINK("#'Menu'!A1","⬅ Voltar ao Menu") -> ⬅ Voltar ao Menu
A2: Despesas dedutíveis
A3: Saúde, educação, previdência etc. A linha 6 é um exemplo — substitua ou apague.
A5: Data | B5: Categoria | C5: Beneficiário/Prestador | D5: CPF/CNPJ do prestador | E5: Valor (R$) | F5: Comprovante em mãos? | G5: Observação
A6: 46093 | B6: Saúde | C6: Clínica Exemplo | D6: 11222333000144 | E6: 350 | F6: Sim | G6: Exemplo

Sheet Bens e Direitos
A1: =HYPERLINK("#'Menu'!A1","⬅ Voltar ao Menu") -> ⬅ Voltar ao Menu
A2: Bens e Direitos
A3: Valores em 31/12. A linha 6 é um exemplo — substitua ou apague.
A5: Grupo | B5: Descrição | C5: Data de aquisição | D5: Situação em 31/12 do ano anterior (R$) | E5: Situação em 31/12 do ano-calendário (R$) | F5: Variação (R$) | G5: Observação
A6: Veículo | B6: Carro Exemplo 2020 | C6: 43997 | D6: 45000 | E6: 42000 | F6: =IF(AND(D6="",E6=""),"",N(E6)-N(D6)) -> -3000 | G6: Exemplo
F7: =IF(AND(D7="",E7=""),"",N(E7)-N(D7))
F8: =IF(AND(D8="",E8=""),"",N(E8)-N(D8))
F9: =IF(AND(D9="",E9=""),"",N(E9)-N(D9))
F10: =IF(AND(D10="",E10=""),"",N(E10)-N(D10))
F11: =IF(AND(D11="",E11=""),"",N(E11)-N(D11))
F12: =IF(AND(D12="",E12=""),"",N(E12)-N(D12))
F13: =IF(AND(D13="",E13=""),"",N(E13)-N(D13))
F14: =IF(AND(D14="",E14=""),"",N(E14)-N(D14))
F15: =IF(AND(D15="",E15=""),"",N(E15)-N(D15))
F16: =IF(AND(D16="",E16=""),"",N(E16)-N(D16))
F17: =IF(AND(D17="",E17=""),"",N(E17)-N(D17))
F18: =IF(AND(D18="",E18=""),"",N(E18)-N(D18))
... F205: =IF(AND(D205="",E205=""),"",N(E205)-N(D205))

Sheet Dívidas
A1: =HYPERLINK("#'Menu'!A1","⬅ Voltar ao Menu") -> ⬅ Voltar ao Menu
A2: Dívidas e ônus
A3: Financiamentos, empréstimos etc. A linha 6 é um exemplo — substitua ou apague.
A5: Credor | B5: CPF/CNPJ do credor | C5: Descrição | D5: Saldo em 31/12 do ano anterior (R$) | E5: Saldo em 31/12 do ano-calendário (R$) | F5: Observação
A6: Banco Exemplo S.A. | B6: 00111222000133 | C6: Financiamento do carro | D6: 20000 | E6: 15000 | F6: Exemplo

Sheet Checklist
A1: =HYPERLINK("#'Menu'!A1","⬅ Voltar ao Menu") -> ⬅ Voltar ao Menu
A2: Checklist de documentos
A3: Atualize o status conforme for reunindo cada documento.
A5: Documento | B5: Status | C5: Observação
A6: Informe de rendimentos (empregador/fontes pagadoras) | B6: Pendente
A7: Informes de rendimentos de bancos e corretoras | B7: Pendente
A8: Informe do plano de saúde | B8: Pendente
A9: Recibos e notas de despesas médicas | B9: Pendente
A10: Comprovantes de despesas com educação | B10: Pendente
A11: Documentos de imóveis (escritura, IPTU, financiamento) | B11: Pendente
A12: Documentos de veículos (CRLV, financiamento) | B12: Pendente
A13: Extratos de investimentos e criptoativos | B13: Pendente
A14: Dados e CPF dos dependentes | B14: Pendente
A15: Comprovante de pensão alimentícia / previdência privada | B15: Pendente
A16: Recibo da declaração do ano anterior | B16: Pendente
A17: Dados bancários para restituição | B17: Pendente
A19: Progresso | B19: =IF(COUNTA(A6:A17)=0,0,COUNTIF(B6:B17,"Entregue")/COUNTA(A6:A17)) -> 0

Sheet Listas
A1: =HYPERLINK("#'Menu'!A1","⬅ Voltar ao Menu") -> ⬅ Voltar ao Menu
A2: Listas de apoio
A3: Alimentam os menus suspensos. Edite com cuidado.
A5: Tipo de rendimento | B5: Categoria de despesa | C5: Grupo de bem | D5: Sim/Não | E5: UF | F5: Estado civil | G5: Parentesco | H5: Status
A6: Tributável (salário, aluguel, autônomo) | B6: Saúde | C6: Imóvel | D6: Sim | E6: AC | F6: Solteiro(a) | G6: Filho(a) | H6: Pendente
A7: Isento e não tributável | B7: Educação | C7: Veículo | D7: Não | E7: AL | F7: Casado(a) | G7: Cônjuge/Companheiro(a) | H7: Em andamento
A8: Tributação exclusiva/definitiva | B8: Previdência (PGBL) | C8: Conta bancária | E8: AP | F8: União estável | G8: Pai/Mãe | H8: Entregue
A9: Outros | B9: Pensão alimentícia | C9: Aplicação financeira | E9: AM | F9: Divorciado(a) | G9: Outro
B10: Doação | C10: Participação societária | E10: BA | F10: Viúvo(a)
B11: Outras | C11: Criptoativos | E11: CE
C12: Outros bens | E12: DF
E13: ES
E14: GO
E15: MA
E16: MT
E17: MS
E18: MG
E19: PA
E20: PB
E21: PR
E22: PE
E23: PI
E24: RJ
... E32: TO
